multiplexer32.v
// 32 bit 2 into 1 mux
module mux32 (OUTPUT, INPUT1, INPUT2, SELECT);
    input SELECT;
    input[31:0] INPUT1, INPUT2;
    output reg [31:0] OUTPUT;
    always @(*) begin
        if (SELECT==0) OUTPUT = INPUT1;
        else if (SELECT ==1) OUTPUT = INPUT2;
    end
    
endmodule

cpu.v
`include "reg.v"
`include "alu.v"
`include "multiplexer32.v"
`include "controlUnit.v"





module cpu (PC, INSTRUCTION, CLK, RESET );

    // port declaration
    input CLK, RESET;
    input [18:0] INSTRUCTION;
    output reg [31:0] PC ;
    
    // wires for internal implementation
    wire  IMM_SELECT, WRITE_ENABLE, ZERO,BRANCH,BRAZ,BRANZ,BRAUNCOND, AND_OUT, OR_OUT, AND_OUT2, MOV_SELECT;

    wire [2:0] ALUOP;
    wire [31:0] NEXTPC,B_MUX_OUT, ADDR_OUT, NEXTPC2, ALU_OUT,  OUT1, OUT2, IMM_RESULT, SIGN_EXTENDED_IMM,PC_PLUS_IMM, REG_IN;
    
    //  initiating the modules    
    controlUnit mucu(ALUOP, WRITE_ENABLE, IMM_SELECT,BRAZ,BRANZ,BRAUNCOND, INSTRUCTION[18:15],MOV_SELECT);
    reg_file myregfile(REG_IN, OUT1, OUT2, INSTRUCTION[14:10],INSTRUCTION[9:5], INSTRUCTION[4:0],  WRITE_ENABLE, CLK, RESET);
   
    signExtend signex(SIGN_EXTENDED_IMM, INSTRUCTION[14:0]);

    mux32 immediate_or_reg(IMM_RESULT, OUT2, SIGN_EXTENDED_IMM, IMM_SELECT);

    Alu alu(ALU_OUT, OUT1, IMM_RESULT, ALUOP);  
    addr adr(NEXTPC, PC, 'd1);
    addr adr2(PC_PLUS_IMM, PC, SIGN_EXTENDED_IMM);

    andgate a1(AND_OUT, BRAZ, ZERO);
    andgate a2(AND_OUT2, BRANZ, ~ZERO);
    orgate or1(OR_OUT,AND_OUT, AND_OUT2, BRAUNCOND);
 
    mux32 jump_mux (NEXTPC2 ,NEXTPC, PC_PLUS_IMM,OR_OUT);
    mux32 move_mux (REG_IN ,ALU_OUT, { {22{INSTRUCTION[9]}}, INSTRUCTION[9:0] },MOV_SELECT);

    
    // pc update with clock
    always @(posedge CLK) begin
        if(RESET) PC = 0;
        else #1 PC = NEXTPC2;
    end

endmodule

// adder
module addr (NEXTPC, PC, ONE);

    input [31:0] PC, ONE ;
    output [31:0] NEXTPC;
    assign  #1 NEXTPC =  PC + ONE;
    
endmodule

// adder
module signExtend (NEW_VAL, CURRENT_VAL);

    input[14:0] CURRENT_VAL;
    output [31:0] NEW_VAL;
    assign NEW_VAL = { {17{CURRENT_VAL[31]}}, CURRENT_VAL };
   
    
endmodule

// AND GATE
module andgate (OUTPUT, INPUT1, INPUT2);
    input INPUT1, INPUT2;
    output OUTPUT;
    assign OUTPUT = INPUT1 & INPUT2;
endmodule

// OR GATE
module orgate (OUTPUT, INPUT1, INPUT2, INPUT3);
    input INPUT1, INPUT2, INPUT3;
    output OUTPUT;
    assign OUTPUT = INPUT1 | INPUT2 | INPUT3;
endmodule

alu.v
module Alu ( RESULT, DATA1, DATA2, SELECT);

// port declaration
input [31:0] DATA1, DATA2;
input [2:0] SELECT;
output reg [31:0] RESULT;





wire [31:0] ADD_OUT, FORWARD_OUT, AND_OUT, OR_OUT,SUB_OUT;


// module initialize
Forward fwd1(FORWARD_OUT, DATA2 );
Add add1(ADD_OUT, DATA1, DATA2 );
Sub sub1(SUB_OUT, DATA1, DATA2 );
And and1(AND_OUT, DATA1, DATA2 );
Or or1(OR_OUT, DATA1, DATA2 );





// assign ZERO = ~(|RESULT);


always @(*) begin //always @(*) begin
    
    
    
      
    case (SELECT)
        'b000:
            RESULT = ADD_OUT;
        'b001:
            RESULT = SUB_OUT; 
        'b010:
            RESULT = AND_OUT; 
        'b011:
            RESULT = OR_OUT; 
        'b100:
            RESULT = FORWARD_OUT; 
        default:
            RESULT = 'b00000000;

    endcase

end


endmodule

// arithmatic modules

module Forward (FORWARD_OUT, DATA2);
    input [31:0]  DATA2;
    output [31:0] FORWARD_OUT;
    assign #1 FORWARD_OUT =  DATA2; 
    
endmodule

module Add (ADD_OUT, DATA1, DATA2);
    input [31:0] DATA1, DATA2;
    output [31:0] ADD_OUT;
    assign #2  ADD_OUT =  DATA1+DATA2; 
    
endmodule

module Sub (ADD_OUT, DATA1, DATA2);
    input [31:0] DATA1, DATA2;
    output [31:0] ADD_OUT;
    assign #2  ADD_OUT =  DATA1-DATA2; 
    
endmodule

module And (AND_OUT, DATA1, DATA2);
    input [31:0] DATA1, DATA2;
    output [31:0] AND_OUT;
    assign #1 AND_OUT =  DATA1 & DATA2; 
    
endmodule

module Or (OR_OUT, DATA1, DATA2);
    input [31:0] DATA1, DATA2;
    output [31:0] OR_OUT;
    assign  #1 OR_OUT =  DATA1 | DATA2; 
    
endmodule

reg.v
module reg_file(IN, OUT1, OUT2, INADDRESS, OUT1ADDRESS, OUT2ADDRESS, WRITE, CLK, RESET);

	input WRITE, CLK, RESET;				// 1-bit inputs
	input [4:0] INADDRESS, OUT1ADDRESS, OUT2ADDRESS;	// 5-bits inputs
	input [31:0] IN;						// 32-bits input

	output [31:0] OUT1, OUT2;				// 32-bits outputs

	reg [31:0] registers[0:31];		// this represents the 32-bits(4 byte)  32 registers


	integer regNum ;			// represet the register number for the RESET task
       
 integer i,f;  
	// assign given addresses values to OUT1 and OUT2 respectively. this is asynchronous therefore, we use blocking statement with delay 2 units
	assign #2 OUT1 = registers[OUT1ADDRESS];	
	assign #2 OUT2 = registers[OUT2ADDRESS];


	// write to given address register at positive edge of the clock
	always @(posedge CLK) 
	begin 
		// writting happens when WRITE is high. 
		// if statement includes only one row so don't use begin end keywords
		if (RESET == 0 && WRITE ==1 )	
			
			// this is synchronous therefore, we use non-blocking statement with delay 1 unit.
			// write in to given register
			#1 registers[INADDRESS] <= IN ;

		
		// reset all the registers when RESET is high. 
		if ( RESET ) #1
		begin
			
			for(regNum = 0; regNum < 32 ; regNum = regNum + 1)begin
			
				registers[regNum] <= 32'b0;

			end
			
			
			
		end
	
	end


    initial
    
    begin
        $dumpfile("cpu_wavedata.vcd");
        for(i=0;i<32;i++)
            $dumpvars(1,registers[i]);
    end   


	initial begin
		#200
  		f = $fopen("output.txt","w");
	end

	initial begin
		#210
  		for (i = 0; i<32; i=i+1)
    	$fwrite(f,"{instr_mem[%d]}= 32'b%b;\n",i,registers[i]);
	end

	initial begin
		#215
  		$fclose(f);  
	end

endmodule

controlUnit.v
module   controlUnit(ALUOP, WRITEENABLE, MUXIMM,BRAZ,BRANZ,BRAUNCOND, OPCODE);
    input [3:0] OPCODE;
    output reg WRITEENABLE, MUXIMM, BRAZ,BRANZ,BRAUNCOND;
    output reg [2:0] ALUOP;

    always @(*) begin
        #1
        case (OPCODE)   /// INSTRUCTION[31:24]
            
            'b0000: begin // add
                MUXIMM = 'b0 ;
                ALUOP = 3'b000;
                WRITEENABLE = 'b1;
                BRAZ = 'b0;
                BRANZ = 'b0;
                BRAUNCOND = 'b0;
            end 

            'b0001: begin // addi
                MUXIMM = 'b1 ;
                ALUOP = 3'b000;
                WRITEENABLE = 'b1;
                BRAZ = 'b0;
                BRANZ = 'b0;
                BRAUNCOND = 'b0;
            end

            'b0010: begin // sub
                MUXIMM = 'b0 ;
                ALUOP = 3'b001;
                WRITEENABLE = 'b1;
                BRAZ = 'b0;
                BRANZ = 'b0;
                BRAUNCOND = 'b0;
            end 

            'b0011: begin // subi
                MUXIMM = 'b1 ;
                ALUOP = 3'b001;
                WRITEENABLE = 'b1;
                BRAZ = 'b0;
                BRANZ = 'b0;
                BRAUNCOND = 'b0;
            end 

             'b0100: begin // and
                MUXIMM = 'b0 ;
                ALUOP = 3'b010;
                WRITEENABLE = 'b1;
                BRAZ = 'b0;
                BRANZ = 'b0;
                BRAUNCOND = 'b0;
            end 

            'b0101: begin // andi
                MUXIMM = 'b1 ;
                ALUOP = 3'b010;
                WRITEENABLE = 'b1;
                BRAZ = 'b0;
                BRANZ = 'b0;
                BRAUNCOND = 'b0;
            end  

            'b0110: begin // or
                MUXIMM = 'b0 ;
                ALUOP = 3'b011;
                WRITEENABLE = 'b1;
                BRAZ = 'b0;
                BRANZ = 'b0;
                BRAUNCOND = 'b0;
            end 

            'b0111: begin // ori
                MUXIMM = 'b1 ;
                ALUOP = 3'b011;
                WRITEENABLE = 'b1;
                BRAZ = 'b0;
                BRANZ = 'b0;
                BRAUNCOND = 'b0;
            end   

            'b1000: begin // mov
                MUXIMM = 'b1 ;
                ALUOP = 3'b100;
                WRITEENABLE = 'b1;
                BRAZ = 'b0;
                BRANZ = 'b0;
                BRAUNCOND = 'b0;
            end 

            'b1001: begin // Branz
                MUXIMM = 'b0 ;
                ALUOP = 3'bxxx;
                WRITEENABLE = 'bx;
                BRAZ = 'b0;
                BRANZ = 'b1;
                BRAUNCOND = 'b0;
            end 

            'b1010: begin // Braz
                MUXIMM = 'b0 ;
                ALUOP = 3'bxxx;
                WRITEENABLE = 'bx;
                BRAZ = 'b1;
                BRANZ = 'b0;
                BRAUNCOND = 'b0;
            end      
    
            'b1011: begin // Brauncod
                MUXIMM = 'bx ;
                ALUOP = 3'bxxx;
                WRITEENABLE = 'bx;
                BRAZ = 'b0;
                BRANZ = 'b0;
                BRAUNCOND = 'b1;
            end 

            default: begin 
                MUXIMM = 'bx ;
                ALUOP = 3'bxxx;
                WRITEENABLE = 'bx;
                BRAZ = 'bx;
                BRANZ = 'bx;
                BRAUNCOND = 'bx;
            end              


                
        endcase   
    end
endmodule

cpu_tb.v

`include "cpu.v"

module cpu_tb;

    reg CLK, RESET;
    wire [31:0] PC ;
    wire [18:0] INSTRUCTION;
    
   
	
	reg [18:0] instr_mem [127:0]; 	// instruction array
    
   integer i;  
    
	assign #2 INSTRUCTION = {instr_mem[PC]};	// fetching instruction with time delay
	
    initial
    begin
        // initializin ram module
       

    //    // Unconditional Branch
	// 	{instr_mem[0] }= 19'b1000000010001000001;
    //     {instr_mem[1] }= 19'b1000000010001000001;
    //     {instr_mem[2] }= 19'b1000000100001000010;
    //     {instr_mem[3] }= 19'b100000011xxxxx00010;

    //     {instr_mem[4] }= 19'b0000001000000100010;
    //     {instr_mem[5] }= 19'b0001001010010000101;
    //     {instr_mem[6] }= 19'b0010001100010100010;

    //     {instr_mem[7] }= 19'b0011001100001000001;
    //     {instr_mem[8] }= 19'b0100001110001100101;
    //     {instr_mem[9] }= 19'b0101001110011000111;

    //     {instr_mem[10]} = 19'b0110010000011100000;
    //     {instr_mem[11]} = 19'b0111010000011100100;
    //     {instr_mem[12]} = 19'b1011xxxxxxxxxx01010;

        


         // BRANZ
        // {instr_mem[0] }= 19'b1000000000000000001;
        // {instr_mem[1] }= 19'b1000000010001000001;
        // {instr_mem[2] }= 19'b1000000100001000010;
        // {instr_mem[3] }= 19'b1000000110000000010;

        // {instr_mem[4] }= 19'b0000001000000100010;
        // {instr_mem[5] }= 19'b0001001010010000101;
        // {instr_mem[6] }= 19'b0010001100010100010;

        // {instr_mem[7] }= 19'b0011001100001000001;
        // {instr_mem[8] }= 19'b0100001110001100101;
        // {instr_mem[9] }= 19'b0101001110011000111;

        // {instr_mem[10]} = 19'b0110010000011100000;
        // {instr_mem[11]} = 19'b0111010000011100100;
        // {instr_mem[12]} = 19'b1001000100000100101;
        // {instr_mem[12]} = 19'boooo11111xxxxx88888;
        {instr_mem[0] }=     19'b1000000100000000010 ; // r2 = 2
        {instr_mem[1] }=     19'b1000000110000100001;  // r3 = 33
        {instr_mem[2] }=     19'b0000000010001000011;  // r1 =  r2 + r3
        {instr_mem[3] }=     19'b0001001000000100100; //  r4 = r1 + #4
        {instr_mem[4] }=     19'b1001000000000000010; // branz #2
        {instr_mem[5] }=     19'b1000001010000010001; // not execute due to branz
        {instr_mem[6] }=     19'b1000001010000001010; // r5 = r0 + r10  

        // r2 =3
        // r3 = 33
        // r1 = 35
        // r4 = 39
        // r5 = 0
        

        // BRAZ

        //  {instr_mem[0] }= 19'b1000000010001000001;
        // {instr_mem[1] }= 19'b1000000010001000001;
        // {instr_mem[2] }= 19'b1000000100001000010;
        // {instr_mem[3] }= 19'b100000011xxxxx00010;

        // {instr_mem[4] }= 19'b0000001000000100010;
        // {instr_mem[5] }= 19'b0001001010010000101;
        // {instr_mem[6] }= 19'b0010001100010100010;

        // {instr_mem[7] }= 19'b0011001100001000001;
        // {instr_mem[8] }= 19'b0100001110001100101;
        // {instr_mem[9] }= 19'b0101001110011000111;

        // {instr_mem[10]} = 19'b0110010000011100000;
        // {instr_mem[11]} = 19'b0111010000011100100;
        // {instr_mem[12]} = 19'b1010000100001000101;
       


        // {instr_mem[15]} = 19'b1001001000001001001;
        // {instr_mem[16]} = 19'b0110110110000110110;
        // {instr_mem[17]} = 19'b1101101100001101101;
        // {instr_mem[18]} = 19'b0010010010000010010;
        // {instr_mem[19]} = 19'b1011011010001011011;
        
    end
    

    initial
    begin
        $dumpfile("cpu_wavedata.vcd");
        for(i=0;i<20;i++)
            $dumpvars(1,instr_mem[i]);
    end    
    /* 
    -----
     CPU
    -----
    */
    cpu mycpu(PC, INSTRUCTION, CLK, RESET);

    initial
    begin
    
        // generate files needed to plot the waveform using GTKWave
        $dumpfile("cpu_wavedata.vcd");
		$dumpvars(0, cpu_tb);
        
        CLK = 1'b0;
        RESET = 1'b0;
        
        // TODO: Reset the CPU (by giving a pulse to RESET signal) to start the proginstr_mem exe}cution
        RESET = 1'b1;
        #6
        RESET = 1'b0;

        // reset check
        #250
        RESET = 1'b1;
        #2
        RESET = 1'b0;
        //
		
		
        // finish simulation after some time
        #500
        $finish;
        
    end
    
    // clock signal generation
    always
        #4 CLK = ~CLK;
        

endmodule

cpu_wavedata.vcd
$date
	Sun May 28 08:15:22 2023
$end
$version
	Icarus Verilog
$end
$timescale
	1s
$end
$scope module cpu_tb $end
$scope module mycpu $end
$scope module myregfile $end
$var reg 32 ! \registers[0] [31:0] $end
$upscope $end
$upscope $end
$upscope $end
$scope module cpu_tb $end
$scope module mycpu $end
$scope module myregfile $end
$var reg 32 " \registers[1] [31:0] $end
$upscope $end
$upscope $end
$upscope $end
$scope module cpu_tb $end
$scope module mycpu $end
$scope module myregfile $end
$var reg 32 # \registers[2] [31:0] $end
$upscope $end
$upscope $end
$upscope $end
$scope module cpu_tb $end
$scope module mycpu $end
$scope module myregfile $end
$var reg 32 $ \registers[3] [31:0] $end
$upscope $end
$upscope $end
$upscope $end
$scope module cpu_tb $end
$scope module mycpu $end
$scope module myregfile $end
$var reg 32 % \registers[4] [31:0] $end
$upscope $end
$upscope $end
$upscope $end
$scope module cpu_tb $end
$scope module mycpu $end
$scope module myregfile $end
$var reg 32 & \registers[5] [31:0] $end
$upscope $end
$upscope $end
$upscope $end
$scope module cpu_tb $end
$scope module mycpu $end
$scope module myregfile $end
$var reg 32 ' \registers[6] [31:0] $end
$upscope $end
$upscope $end
$upscope $end
$scope module cpu_tb $end
$scope module mycpu $end
$scope module myregfile $end
$var reg 32 ( \registers[7] [31:0] $end
$upscope $end
$upscope $end
$upscope $end
$scope module cpu_tb $end
$scope module mycpu $end
$scope module myregfile $end
$var reg 32 ) \registers[8] [31:0] $end
$upscope $end
$upscope $end
$upscope $end
$scope module cpu_tb $end
$scope module mycpu $end
$scope module myregfile $end
$var reg 32 * \registers[9] [31:0] $end
$upscope $end
$upscope $end
$upscope $end
$scope module cpu_tb $end
$scope module mycpu $end
$scope module myregfile $end
$var reg 32 + \registers[10] [31:0] $end
$upscope $end
$upscope $end
$upscope $end
$scope module cpu_tb $end
$scope module mycpu $end
$scope module myregfile $end
$var reg 32 , \registers[11] [31:0] $end
$upscope $end
$upscope $end
$upscope $end
$scope module cpu_tb $end
$scope module mycpu $end
$scope module myregfile $end
$var reg 32 - \registers[12] [31:0] $end
$upscope $end
$upscope $end
$upscope $end
$scope module cpu_tb $end
$scope module mycpu $end
$scope module myregfile $end
$var reg 32 . \registers[13] [31:0] $end
$upscope $end
$upscope $end
$upscope $end
$scope module cpu_tb $end
$scope module mycpu $end
$scope module myregfile $end
$var reg 32 / \registers[14] [31:0] $end
$upscope $end
$upscope $end
$upscope $end
$scope module cpu_tb $end
$scope module mycpu $end
$scope module myregfile $end
$var reg 32 0 \registers[15] [31:0] $end
$upscope $end
$upscope $end
$upscope $end
$scope module cpu_tb $end
$scope module mycpu $end
$scope module myregfile $end
$var reg 32 1 \registers[16] [31:0] $end
$upscope $end
$upscope $end
$upscope $end
$scope module cpu_tb $end
$scope module mycpu $end
$scope module myregfile $end
$var reg 32 2 \registers[17] [31:0] $end
$upscope $end
$upscope $end
$upscope $end
$scope module cpu_tb $end
$scope module mycpu $end
$scope module myregfile $end
$var reg 32 3 \registers[18] [31:0] $end
$upscope $end
$upscope $end
$upscope $end
$scope module cpu_tb $end
$scope module mycpu $end
$scope module myregfile $end
$var reg 32 4 \registers[19] [31:0] $end
$upscope $end
$upscope $end
$upscope $end
$scope module cpu_tb $end
$scope module mycpu $end
$scope module myregfile $end
$var reg 32 5 \registers[20] [31:0] $end
$upscope $end
$upscope $end
$upscope $end
$scope module cpu_tb $end
$scope module mycpu $end
$scope module myregfile $end
$var reg 32 6 \registers[21] [31:0] $end
$upscope $end
$upscope $end
$upscope $end
$scope module cpu_tb $end
$scope module mycpu $end
$scope module myregfile $end
$var reg 32 7 \registers[22] [31:0] $end
$upscope $end
$upscope $end
$upscope $end
$scope module cpu_tb $end
$scope module mycpu $end
$scope module myregfile $end
$var reg 32 8 \registers[23] [31:0] $end
$upscope $end
$upscope $end
$upscope $end
$scope module cpu_tb $end
$scope module mycpu $end
$scope module myregfile $end
$var reg 32 9 \registers[24] [31:0] $end
$upscope $end
$upscope $end
$upscope $end
$scope module cpu_tb $end
$scope module mycpu $end
$scope module myregfile $end
$var reg 32 : \registers[25] [31:0] $end
$upscope $end
$upscope $end
$upscope $end
$scope module cpu_tb $end
$scope module mycpu $end
$scope module myregfile $end
$var reg 32 ; \registers[26] [31:0] $end
$upscope $end
$upscope $end
$upscope $end
$scope module cpu_tb $end
$scope module mycpu $end
$scope module myregfile $end
$var reg 32 < \registers[27] [31:0] $end
$upscope $end
$upscope $end
$upscope $end
$scope module cpu_tb $end
$scope module mycpu $end
$scope module myregfile $end
$var reg 32 = \registers[28] [31:0] $end
$upscope $end
$upscope $end
$upscope $end
$scope module cpu_tb $end
$scope module mycpu $end
$scope module myregfile $end
$var reg 32 > \registers[29] [31:0] $end
$upscope $end
$upscope $end
$upscope $end
$scope module cpu_tb $end
$scope module mycpu $end
$scope module myregfile $end
$var reg 32 ? \registers[30] [31:0] $end
$upscope $end
$upscope $end
$upscope $end
$scope module cpu_tb $end
$scope module mycpu $end
$scope module myregfile $end
$var reg 32 @ \registers[31] [31:0] $end
$upscope $end
$upscope $end
$upscope $end
$scope module cpu_tb $end
$var reg 19 A \instr_mem[0] [18:0] $end
$upscope $end
$scope module cpu_tb $end
$var reg 19 B \instr_mem[1] [18:0] $end
$upscope $end
$scope module cpu_tb $end
$var reg 19 C \instr_mem[2] [18:0] $end
$upscope $end
$scope module cpu_tb $end
$var reg 19 D \instr_mem[3] [18:0] $end
$upscope $end
$scope module cpu_tb $end
$var reg 19 E \instr_mem[4] [18:0] $end
$upscope $end
$scope module cpu_tb $end
$var reg 19 F \instr_mem[5] [18:0] $end
$upscope $end
$scope module cpu_tb $end
$var reg 19 G \instr_mem[6] [18:0] $end
$upscope $end
$scope module cpu_tb $end
$var reg 19 H \instr_mem[7] [18:0] $end
$upscope $end
$scope module cpu_tb $end
$var reg 19 I \instr_mem[8] [18:0] $end
$upscope $end
$scope module cpu_tb $end
$var reg 19 J \instr_mem[9] [18:0] $end
$upscope $end
$scope module cpu_tb $end
$var reg 19 K \instr_mem[10] [18:0] $end
$upscope $end
$scope module cpu_tb $end
$var reg 19 L \instr_mem[11] [18:0] $end
$upscope $end
$scope module cpu_tb $end
$var reg 19 M \instr_mem[12] [18:0] $end
$upscope $end
$scope module cpu_tb $end
$var reg 19 N \instr_mem[13] [18:0] $end
$upscope $end
$scope module cpu_tb $end
$var reg 19 O \instr_mem[14] [18:0] $end
$upscope $end
$scope module cpu_tb $end
$var reg 19 P \instr_mem[15] [18:0] $end
$upscope $end
$scope module cpu_tb $end
$var reg 19 Q \instr_mem[16] [18:0] $end
$upscope $end
$scope module cpu_tb $end
$var reg 19 R \instr_mem[17] [18:0] $end
$upscope $end
$scope module cpu_tb $end
$var reg 19 S \instr_mem[18] [18:0] $end
$upscope $end
$scope module cpu_tb $end
$var reg 19 T \instr_mem[19] [18:0] $end
$upscope $end
$scope module cpu_tb $end
$var wire 32 U PC [31:0] $end
$var wire 19 V INSTRUCTION [18:0] $end
$var reg 1 W CLK $end
$var reg 1 X RESET $end
$var integer 32 Y i [31:0] $end
$scope module mycpu $end
$var wire 1 W CLK $end
$var wire 19 Z INSTRUCTION [18:0] $end
$var wire 1 [ MOV_SELECT $end
$var wire 1 X RESET $end
$var wire 1 \ ZERO $end
$var wire 1 ] WRITE_ENABLE $end
$var wire 32 ^ SIGN_EXTENDED_IMM [31:0] $end
$var wire 32 _ REG_IN [31:0] $end
$var wire 32 ` PC_PLUS_IMM [31:0] $end
$var wire 32 a OUT2 [31:0] $end
$var wire 32 b OUT1 [31:0] $end
$var wire 1 c OR_OUT $end
$var wire 32 d NEXTPC2 [31:0] $end
$var wire 32 e NEXTPC [31:0] $end
$var wire 1 f IMM_SELECT $end
$var wire 32 g IMM_RESULT [31:0] $end
$var wire 1 h BRAZ $end
$var wire 1 i BRAUNCOND $end
$var wire 1 j BRANZ $end
$var wire 1 k AND_OUT2 $end
$var wire 1 l AND_OUT $end
$var wire 32 m ALU_OUT [31:0] $end
$var wire 3 n ALUOP [2:0] $end
$var reg 32 o PC [31:0] $end
$scope module a1 $end
$var wire 1 \ INPUT2 $end
$var wire 1 l OUTPUT $end
$var wire 1 h INPUT1 $end
$upscope $end
$scope module a2 $end
$var wire 1 p INPUT2 $end
$var wire 1 k OUTPUT $end
$var wire 1 j INPUT1 $end
$upscope $end
$scope module adr $end
$var wire 32 q ONE [31:0] $end
$var wire 32 r PC [31:0] $end
$var wire 32 s NEXTPC [31:0] $end
$upscope $end
$scope module adr2 $end
$var wire 32 t PC [31:0] $end
$var wire 32 u ONE [31:0] $end
$var wire 32 v NEXTPC [31:0] $end
$upscope $end
$scope module alu $end
$var wire 32 w SUB_OUT [31:0] $end
$var wire 3 x SELECT [2:0] $end
$var wire 32 y OR_OUT [31:0] $end
$var wire 32 z FORWARD_OUT [31:0] $end
$var wire 32 { DATA2 [31:0] $end
$var wire 32 | DATA1 [31:0] $end
$var wire 32 } AND_OUT [31:0] $end
$var wire 32 ~ ADD_OUT [31:0] $end
$var reg 32 !" RESULT [31:0] $end
$scope module add1 $end
$var wire 32 "" DATA2 [31:0] $end
$var wire 32 #" DATA1 [31:0] $end
$var wire 32 $" ADD_OUT [31:0] $end
$upscope $end
$scope module and1 $end
$var wire 32 %" AND_OUT [31:0] $end
$var wire 32 &" DATA2 [31:0] $end
$var wire 32 '" DATA1 [31:0] $end
$upscope $end
$scope module fwd1 $end
$var wire 32 (" FORWARD_OUT [31:0] $end
$var wire 32 )" DATA2 [31:0] $end
$upscope $end
$scope module or1 $end
$var wire 32 *" OR_OUT [31:0] $end
$var wire 32 +" DATA2 [31:0] $end
$var wire 32 ," DATA1 [31:0] $end
$upscope $end
$scope module sub1 $end
$var wire 32 -" DATA2 [31:0] $end
$var wire 32 ." DATA1 [31:0] $end
$var wire 32 /" ADD_OUT [31:0] $end
$upscope $end
$upscope $end
$scope module immediate_or_reg $end
$var wire 1 f SELECT $end
$var wire 32 0" INPUT2 [31:0] $end
$var wire 32 1" INPUT1 [31:0] $end
$var reg 32 2" OUTPUT [31:0] $end
$upscope $end
$scope module jump_mux $end
$var wire 32 3" INPUT1 [31:0] $end
$var wire 32 4" INPUT2 [31:0] $end
$var wire 1 c SELECT $end
$var reg 32 5" OUTPUT [31:0] $end
$upscope $end
$scope module move_mux $end
$var wire 32 6" INPUT1 [31:0] $end
$var wire 32 7" INPUT2 [31:0] $end
$var wire 1 [ SELECT $end
$var reg 32 8" OUTPUT [31:0] $end
$upscope $end
$scope module mucu $end
$var wire 4 9" OPCODE [3:0] $end
$var reg 3 :" ALUOP [2:0] $end
$var reg 1 j BRANZ $end
$var reg 1 i BRAUNCOND $end
$var reg 1 h BRAZ $end
$var reg 1 f MUXIMM $end
$var reg 1 ] WRITEENABLE $end
$upscope $end
$scope module myregfile $end
$var wire 1 W CLK $end
$var wire 32 ;" IN [31:0] $end
$var wire 5 <" INADDRESS [4:0] $end
$var wire 32 =" OUT1 [31:0] $end
$var wire 5 >" OUT1ADDRESS [4:0] $end
$var wire 32 ?" OUT2 [31:0] $end
$var wire 5 @" OUT2ADDRESS [4:0] $end
$var wire 1 X RESET $end
$var wire 1 ] WRITE $end
$var integer 32 A" f [31:0] $end
$var integer 32 B" i [31:0] $end
$var integer 32 C" regNum [31:0] $end
$upscope $end
$scope module or1 $end
$var wire 1 l INPUT1 $end
$var wire 1 k INPUT2 $end
$var wire 1 i INPUT3 $end
$var wire 1 c OUTPUT $end
$upscope $end
$scope module signex $end
$var wire 15 D" CURRENT_VAL [14:0] $end
$var wire 32 E" NEW_VAL [31:0] $end
$upscope $end
$upscope $end
$upscope $end
$enddefinitions $end
#0
$dumpvars
bx E"
bx D"
bx C"
b100000 B"
bx A"
bx @"
bx ?"
bx >"
bx ="
bx <"
bx ;"
bx :"
bx 9"
bx 8"
bx 7"
bx 6"
bx 5"
bx 4"
bx 3"
bx 2"
bx 1"
bx 0"
bx /"
bx ."
bx -"
bx ,"
bx +"
bx *"
bx )"
bx ("
bx '"
bx &"
bx %"
bx $"
bx #"
bx ""
bx !"
bx ~
bx }
bx |
bx {
bx z
bx y
bx x
bx w
bx v
bx u
bx t
bx s
bx r
b1 q
zp
bx o
bx n
bx m
xl
xk
xj
xi
xh
bx g
xf
bx e
bx d
xc
bx b
bx a
bx `
bx _
bx ^
x]
z\
z[
bx Z
b10100 Y
1X
0W
bx V
bx U
bx T
bx S
bx R
bx Q
bx P
bx O
bx N
b1001000100000100101 M
b111010000011100100 L
b110010000011100000 K
b101001110011000111 J
b100001110001100101 I
b11001100001000001 H
b10001100010100010 G
b1001010010000101 F
b1000000100010 E
b100000011xxxxx00010 D
b1000000100001000010 C
b1000000010001000001 B
b1000000010001000001 A
bx @
bx ?
bx >
bx =
bx <
bx ;
bx :
bx 9
bx 8
bx 7
bx 6
bx 5
bx 4
bx 3
bx 2
bx 1
bx 0
bx /
bx .
bx -
bx ,
bx +
bx *
bx )
bx (
bx '
bx &
bx %
bx $
bx #
bx "
bx !
$end
#4
b0 U
b0 o
b0 r
b0 t
1W
#5
b0 @
b0 ?
b0 >
b0 =
b0 <
b0 ;
b0 :
b0 9
b0 8
b0 7
b0 6
b0 5
b0 4
b0 3
b0 2
b0 1
b0 0
b0 /
b0 .
b0 -
b0 ,
b0 +
b0 *
b0 )
b0 (
b0 '
b0 &
b0 %
b0 $
b0 #
b0 "
b0 !
b100000 C"
b1 e
b1 s
b1 3"
#6
b1000 9"
b1 <"
b10 >"
b1 @"
bx000010001000001 ^
bx000010001000001 u
bx000010001000001 0"
bx000010001000001 E"
b10001000001 D"
b1000001 7"
b1000000010001000001 V
b1000000010001000001 Z
0X
#7
b1 d
b1 5"
0c
0k
0l
bx000010001000001 g
bx000010001000001 {
bx000010001000001 ""
bx000010001000001 &"
bx000010001000001 )"
bx000010001000001 +"
bx000010001000001 -"
bx000010001000001 2"
0i
0j
0h
1]
b100 n
b100 x
b100 :"
1f
#8
bx000010001000001 m
bx000010001000001 !"
bx000010001000001 6"
bx1xxx1xxxxx1 y
bx1xxx1xxxxx1 *"
bx0000x000x00000x }
bx0000x000x00000x %"
bx000010001000001 z
bx000010001000001 ("
b0 b
b0 |
b0 #"
b0 '"
b0 ,"
b0 ."
b0 ="
b0 a
b0 1"
b0 ?"
0W
#9
bx000010001000001 y
bx000010001000001 *"
b0 }
b0 %"
#12
1W
#13
bx "
b1 U
b1 o
b1 r
b1 t
#14
b10 d
b10 5"
b10 e
b10 s
b10 3"
#15
bx a
bx 1"
bx ?"
#16
0W
#20
1W
#21
bx "
b10 U
b10 o
b10 r
b10 t
#22
b11 d
b11 5"
b11 e
b11 s
b11 3"
#23
bx000100001000010 g
bx000100001000010 {
bx000100001000010 ""
bx000100001000010 &"
bx000100001000010 )"
bx000100001000010 +"
bx000100001000010 -"
bx000100001000010 2"
b10 <"
b10 @"
bx000100001000010 ^
bx000100001000010 u
bx000100001000010 0"
bx000100001000010 E"
b100001000010 D"
b1000010 7"
b1000000100001000010 V
b1000000100001000010 Z
#24
bx000100001000010 m
bx000100001000010 !"
bx000100001000010 6"
bx000100001000010 y
bx000100001000010 *"
bx000100001000010 z
bx000100001000010 ("
0W
#25
b0 a
b0 1"
b0 ?"
#28
1W
#29
bx #
b11 U
b11 o
b11 r
b11 t
#30
b100 d
b100 5"
b100 e
b100 s
b100 3"
#31
bx00011xxxxx00010 g
bx00011xxxxx00010 {
bx00011xxxxx00010 ""
bx00011xxxxx00010 &"
bx00011xxxxx00010 )"
bx00011xxxxx00010 +"
bx00011xxxxx00010 -"
bx00011xxxxx00010 2"
b11 <"
bx >"
bx00011xxxxx00010 ^
bx00011xxxxx00010 u
bx00011xxxxx00010 0"
bx00011xxxxx00010 E"
b11xxxxx00010 D"
bx00010 7"
bx b
bx |
bx #"
bx '"
bx ,"
bx ."
bx ="
bx a
bx 1"
bx ?"
b100000011xxxxx00010 V
b100000011xxxxx00010 Z
