multiplexer32.v
// 32 bit 2 into 1 mux
module mux32 (OUTPUT, INPUT1, INPUT2, SELECT);
    input SELECT;
    input[31:0] INPUT1, INPUT2;
    output reg [31:0] OUTPUT;
    always @(*) begin
        if (SELECT==0) OUTPUT = INPUT1;
        else if (SELECT ==1) OUTPUT = INPUT2;
    end
    
endmodule

cpu.v
`include "reg.v"
`include "alu.v"
`include "multiplexer32.v"
`include "controlUnit.v"





module cpu (PC, INSTRUCTION, CLK, RESET );

    // port declaration
    input CLK, RESET;
    input [18:0] INSTRUCTION;
    output reg [31:0] PC ;
    
    // wires for internal implementation
    wire  IMM_SELECT, WRITE_ENABLE, ZERO,BRANCH,BRAZ,BRANZ,BRAUNCOND, AND_OUT, OR_OUT, AND_OUT2;

    wire [2:0] ALUOP;
    wire [31:0] NEXTPC,B_MUX_OUT, ADDR_OUT, NEXTPC2, ALU_OUT,  OUT1, OUT2, IMM_RESULT, SIGN_EXTENDED_IMM;
    
    //  initiating the modules    
    controlUnit mucu(ALUOP, WRITE_ENABLE, IMM_SELECT,BRAZ,BRANZ,BRAUNCOND, INSTRUCTION[18:15]);
    reg_file myregfile(ALU_OUT, OUT1, OUT2, INSTRUCTION[14:10],INSTRUCTION[9:5], INSTRUCTION[4:0],  WRITE_ENABLE, CLK, RESET);
   
    signExtend signex(SIGN_EXTENDED_IMM, INSTRUCTION[4:0]);

    mux32 immediate_or_reg(IMM_RESULT, OUT2, SIGN_EXTENDED_IMM, IMM_SELECT);

    Alu alu(ZERO, ALU_OUT, OUT1, IMM_RESULT, ALUOP);  
    addr adr(NEXTPC, PC, 'd1);

    andgate a1(AND_OUT, BRAZ, ZERO);
    andgate a2(AND_OUT2, BRANZ, ~ZERO);
    or or1(OR_OUT,AND_OUT, AND_OUT2, BRAUNCOND);
 
    mux32 jump_mux (NEXTPC2 ,NEXTPC, SIGN_EXTENDED_IMM,OR_OUT);

    
    // pc update with clock
    always @(posedge CLK) begin
        if(RESET) PC = 0;
        else #1 PC = NEXTPC2;
    end

endmodule

// adder
module addr (NEXTPC, PC, ONE);

    input [31:0] PC, ONE ;
    output [31:0] NEXTPC;
    assign  #1 NEXTPC =  PC + ONE;
    
endmodule

// adder
module signExtend (NEW_VAL, CURRENT_VAL);

    input[4:0] CURRENT_VAL;
    output [31:0] NEW_VAL;
    assign NEW_VAL = { {12{1'b0}}, CURRENT_VAL };
    
endmodule

// AND GATE
module andgate (OUTPUT, INPUT1, INPUT2);
    input INPUT1, INPUT2;
    output OUTPUT;
    assign OUTPUT = INPUT1 & INPUT2;
endmodule

// OR GATE
module orgate (OUTPUT, INPUT1, INPUT2);
    input INPUT1, INPUT2;
    output OUTPUT;
    assign OUTPUT = INPUT1 | INPUT2;
endmodule

alu.v
module Alu (ZERO, RESULT, DATA1, DATA2, SELECT);

// port declaration
input [31:0] DATA1, DATA2;
input [2:0] SELECT;
output reg [31:0] RESULT;
output  ZERO;




wire [31:0] ADD_OUT, FORWARD_OUT, AND_OUT, OR_OUT,SUB_OUT;


// module initialize
Forward fwd1(FORWARD_OUT, DATA2 );
Add add1(ADD_OUT, DATA1, DATA2 );
Sub sub1(SUB_OUT, DATA1, DATA2 );
And and1(AND_OUT, DATA1, DATA2 );
Or or1(OR_OUT, DATA1, DATA2 );





assign ZERO = ~(|RESULT);


always @(*) begin //always @(*) begin
    
    
    
      
    case (SELECT)
        'b000:
            RESULT = ADD_OUT;
        'b001:
            RESULT = SUB_OUT; 
        'b010:
            RESULT = AND_OUT; 
        'b011:
            RESULT = OR_OUT; 
        'b100:
            RESULT = FORWARD_OUT; 
        default:
            RESULT = 'b00000000;

    endcase

end


endmodule

// arithmatic modules

module Forward (FORWARD_OUT, DATA2);
    input [31:0]  DATA2;
    output [31:0] FORWARD_OUT;
    assign #1 FORWARD_OUT =  DATA2; 
    
endmodule

module Add (ADD_OUT, DATA1, DATA2);
    input [31:0] DATA1, DATA2;
    output [31:0] ADD_OUT;
    assign #2  ADD_OUT =  DATA1-DATA2; 
    
endmodule

module Sub (ADD_OUT, DATA1, DATA2);
    input [31:0] DATA1, DATA2;
    output [31:0] ADD_OUT;
    assign #2  ADD_OUT =  DATA1+DATA2; 
    
endmodule

module And (AND_OUT, DATA1, DATA2);
    input [31:0] DATA1, DATA2;
    output [31:0] AND_OUT;
    assign #1 AND_OUT =  DATA1 & DATA2; 
    
endmodule

module Or (OR_OUT, DATA1, DATA2);
    input [31:0] DATA1, DATA2;
    output [31:0] OR_OUT;
    assign  #1 OR_OUT =  DATA1 | DATA2; 
    
endmodule

reg.v
module reg_file(IN, OUT1, OUT2, INADDRESS, OUT1ADDRESS, OUT2ADDRESS, WRITE, CLK, RESET);

	input WRITE, CLK, RESET;				// 1-bit inputs
	input [4:0] INADDRESS, OUT1ADDRESS, OUT2ADDRESS;	// 5-bits inputs
	input [31:0] IN;						// 32-bits input

	output [31:0] OUT1, OUT2;				// 32-bits outputs

	reg [31:0] registers[0:31];		// this represents the 32-bits(4 byte)  32 registers


	integer regNum ;			// represet the register number for the RESET task
       
 integer i;  
	// assign given addresses values to OUT1 and OUT2 respectively. this is asynchronous therefore, we use blocking statement with delay 2 units
	assign #2 OUT1 = registers[OUT1ADDRESS];	
	assign #2 OUT2 = registers[OUT2ADDRESS];


	// write to given address register at positive edge of the clock
	always @(posedge CLK) 
	begin 
		// writting happens when WRITE is high. 
		// if statement includes only one row so don't use begin end keywords
		if (RESET == 0 && WRITE ==1 )	
			
			// this is synchronous therefore, we use non-blocking statement with delay 1 unit.
			// write in to given register
			#1 registers[INADDRESS] <= IN ;

		
		// reset all the registers when RESET is high. 
		if ( RESET ) #1
		begin
			
			for(regNum = 0; regNum < 32 ; regNum = regNum + 1)begin
			
				registers[regNum] <= 32'b0;

			end
			
			
			
		end
	
	end


    initial
    
    begin
        $dumpfile("cpu_wavedata.vcd");
        for(i=0;i<32;i++)
            $dumpvars(1,registers[i]);
    end    

endmodule

controlUnit.v
module   controlUnit(ALUOP, WRITEENABLE, MUXIMM,BRAZ,BRANZ,BRAUNCOND, OPCODE);
    input [3:0] OPCODE;
    output reg WRITEENABLE, MUXIMM, BRAZ,BRANZ,BRAUNCOND;
    output reg [2:0] ALUOP;

    always @(*) begin
        #1
        case (OPCODE)   /// INSTRUCTION[31:24]
            
            'b0000: begin // add
                MUXIMM = 'b0 ;
                ALUOP = 3'b000;
                WRITEENABLE = 'b1;
                BRAZ = 'b0;
                BRANZ = 'b0;
                BRAUNCOND = 'b0;
            end 

            'b0001: begin // addi
                MUXIMM = 'b1 ;
                ALUOP = 3'b000;
                WRITEENABLE = 'b1;
                BRAZ = 'b0;
                BRANZ = 'b0;
                BRAUNCOND = 'b0;
            end

            'b0010: begin // sub
                MUXIMM = 'b0 ;
                ALUOP = 3'b001;
                WRITEENABLE = 'b1;
                BRAZ = 'b0;
                BRANZ = 'b0;
                BRAUNCOND = 'b0;
            end 

            'b0011: begin // subi
                MUXIMM = 'b1 ;
                ALUOP = 3'b001;
                WRITEENABLE = 'b1;
                BRAZ = 'b0;
                BRANZ = 'b0;
                BRAUNCOND = 'b0;
            end 

             'b0100: begin // and
                MUXIMM = 'b0 ;
                ALUOP = 3'b010;
                WRITEENABLE = 'b1;
                BRAZ = 'b0;
                BRANZ = 'b0;
                BRAUNCOND = 'b0;
            end 

            'b0101: begin // andi
                MUXIMM = 'b1 ;
                ALUOP = 3'b010;
                WRITEENABLE = 'b1;
                BRAZ = 'b0;
                BRANZ = 'b0;
                BRAUNCOND = 'b0;
            end  

            'b0110: begin // or
                MUXIMM = 'b0 ;
                ALUOP = 3'b011;
                WRITEENABLE = 'b1;
                BRAZ = 'b0;
                BRANZ = 'b0;
                BRAUNCOND = 'b0;
            end 

            'b0111: begin // ori
                MUXIMM = 'b1 ;
                ALUOP = 3'b011;
                WRITEENABLE = 'b1;
                BRAZ = 'b0;
                BRANZ = 'b0;
                BRAUNCOND = 'b0;
            end   

            'b1000: begin // mov
                MUXIMM = 'b1 ;
                ALUOP = 3'b100;
                WRITEENABLE = 'b1;
                BRAZ = 'b0;
                BRANZ = 'b0;
                BRAUNCOND = 'b0;
            end 

            'b1001: begin // Branz
                MUXIMM = 'bx ;
                ALUOP = 3'bxxx;
                WRITEENABLE = 'bx;
                BRAZ = 'b0;
                BRANZ = 'b1;
                BRAUNCOND = 'b0;
            end 

            'b1010: begin // Braz
                MUXIMM = 'bx ;
                ALUOP = 3'bxxx;
                WRITEENABLE = 'bx;
                BRAZ = 'b1;
                BRANZ = 'b0;
                BRAUNCOND = 'b0;
            end      
    
            'b1011: begin // Brauncod
                MUXIMM = 'bx ;
                ALUOP = 3'bxxx;
                WRITEENABLE = 'bx;
                BRAZ = 'b0;
                BRANZ = 'b0;
                BRAUNCOND = 'b1;
            end 

            default: begin 
                MUXIMM = 'bx ;
                ALUOP = 3'bxxx;
                WRITEENABLE = 'bx;
                BRAZ = 'bx;
                BRANZ = 'bx;
                BRAUNCOND = 'bx;
            end              


                
        endcase   
    end
endmodule

cpu_tb.v

`include "cpu.v"

module cpu_tb;

    reg CLK, RESET;
    wire [31:0] PC ;
    wire [18:0] INSTRUCTION;
    
   
	
	reg [18:0] instr_mem [127:0]; 	// instruction array
    
   integer i;  
    
	assign #2 INSTRUCTION = {instr_mem[PC]};	// fetching instruction with time delay
	
    initial
    begin
        // initializin ram module
       
		{instr_mem[0] }= 19'b1000000010001000001;
        {instr_mem[1] }= 19'b1000000010001000001;
        {instr_mem[2] }= 19'b1000000100001000010;
        {instr_mem[3] }= 19'b100000011xxxxx00010;
        {instr_mem[4] }= 19'b1110001110001110001;
        {instr_mem[5] }= 19'b0001110001110001110;
        {instr_mem[6] }= 19'b1001001001001001001;
        {instr_mem[7] }= 19'b0110110110110110110;
        {instr_mem[8] }= 19'b1101101101101101101;
        {instr_mem[9] }= 19'b0010010010010010010;
        {instr_mem[10]} = 19'b1011011011011011011;
        {instr_mem[11]} = 19'b0100100100100100100;
        {instr_mem[12]} = 19'b1110000001110000001;
        {instr_mem[13]} = 19'b0001110000001110000;
        {instr_mem[14]} = 19'b0000001110000001110;
        {instr_mem[15]} = 19'b1001001000001001001;
        {instr_mem[16]} = 19'b0110110110000110110;
        {instr_mem[17]} = 19'b1101101100001101101;
        {instr_mem[18]} = 19'b0010010010000010010;
        {instr_mem[19]} = 19'b1011011010001011011;
        
    end
    

    initial
    begin
        $dumpfile("cpu_wavedata.vcd");
        for(i=0;i<20;i++)
            $dumpvars(1,instr_mem[i]);
    end    
    /* 
    -----
     CPU
    -----
    */
    cpu mycpu(PC, INSTRUCTION, CLK, RESET);

    initial
    begin
    
        // generate files needed to plot the waveform using GTKWave
        $dumpfile("cpu_wavedata.vcd");
		$dumpvars(0, cpu_tb);
        
        CLK = 1'b0;
        RESET = 1'b0;
        
        // TODO: Reset the CPU (by giving a pulse to RESET signal) to start the proginstr_mem exe}cution
        RESET = 1'b1;
        #6
        RESET = 1'b0;

        // reset check
        #67
        RESET = 1'b1;
        #2
        RESET = 1'b0;
        //
		
		
        // finish simulation after some time
        #500
        $finish;
        
    end
    
    // clock signal generation
    always
        #4 CLK = ~CLK;
        

endmodule

cpu_wavedata.vcd
$date
	Fri May 26 00:05:10 2023
$end
$version
	Icarus Verilog
$end
$timescale
	1s
$end
$scope module cpu_tb $end
$scope module mycpu $end
$scope module myregfile $end
$var reg 32 ! \registers[0] [31:0] $end
$upscope $end
$upscope $end
$upscope $end
$scope module cpu_tb $end
$scope module mycpu $end
$scope module myregfile $end
$var reg 32 " \registers[1] [31:0] $end
$upscope $end
$upscope $end
$upscope $end
$scope module cpu_tb $end
$scope module mycpu $end
$scope module myregfile $end
$var reg 32 # \registers[2] [31:0] $end
$upscope $end
$upscope $end
$upscope $end
$scope module cpu_tb $end
$scope module mycpu $end
$scope module myregfile $end
$var reg 32 $ \registers[3] [31:0] $end
$upscope $end
$upscope $end
$upscope $end
$scope module cpu_tb $end
$scope module mycpu $end
$scope module myregfile $end
$var reg 32 % \registers[4] [31:0] $end
$upscope $end
$upscope $end
$upscope $end
$scope module cpu_tb $end
$scope module mycpu $end
$scope module myregfile $end
$var reg 32 & \registers[5] [31:0] $end
$upscope $end
$upscope $end
$upscope $end
$scope module cpu_tb $end
$scope module mycpu $end
$scope module myregfile $end
$var reg 32 ' \registers[6] [31:0] $end
$upscope $end
$upscope $end
$upscope $end
$scope module cpu_tb $end
$scope module mycpu $end
$scope module myregfile $end
$var reg 32 ( \registers[7] [31:0] $end
$upscope $end
$upscope $end
$upscope $end
$scope module cpu_tb $end
$scope module mycpu $end
$scope module myregfile $end
$var reg 32 ) \registers[8] [31:0] $end
$upscope $end
$upscope $end
$upscope $end
$scope module cpu_tb $end
$scope module mycpu $end
$scope module myregfile $end
$var reg 32 * \registers[9] [31:0] $end
$upscope $end
$upscope $end
$upscope $end
$scope module cpu_tb $end
$scope module mycpu $end
$scope module myregfile $end
$var reg 32 + \registers[10] [31:0] $end
$upscope $end
$upscope $end
$upscope $end
$scope module cpu_tb $end
$scope module mycpu $end
$scope module myregfile $end
$var reg 32 , \registers[11] [31:0] $end
$upscope $end
$upscope $end
$upscope $end
$scope module cpu_tb $end
$scope module mycpu $end
$scope module myregfile $end
$var reg 32 - \registers[12] [31:0] $end
$upscope $end
$upscope $end
$upscope $end
$scope module cpu_tb $end
$scope module mycpu $end
$scope module myregfile $end
$var reg 32 . \registers[13] [31:0] $end
$upscope $end
$upscope $end
$upscope $end
$scope module cpu_tb $end
$scope module mycpu $end
$scope module myregfile $end
$var reg 32 / \registers[14] [31:0] $end
$upscope $end
$upscope $end
$upscope $end
$scope module cpu_tb $end
$scope module mycpu $end
$scope module myregfile $end
$var reg 32 0 \registers[15] [31:0] $end
$upscope $end
$upscope $end
$upscope $end
$scope module cpu_tb $end
$scope module mycpu $end
$scope module myregfile $end
$var reg 32 1 \registers[16] [31:0] $end
$upscope $end
$upscope $end
$upscope $end
$scope module cpu_tb $end
$scope module mycpu $end
$scope module myregfile $end
$var reg 32 2 \registers[17] [31:0] $end
$upscope $end
$upscope $end
$upscope $end
$scope module cpu_tb $end
$scope module mycpu $end
$scope module myregfile $end
$var reg 32 3 \registers[18] [31:0] $end
$upscope $end
$upscope $end
$upscope $end
$scope module cpu_tb $end
$scope module mycpu $end
$scope module myregfile $end
$var reg 32 4 \registers[19] [31:0] $end
$upscope $end
$upscope $end
$upscope $end
$scope module cpu_tb $end
$scope module mycpu $end
$scope module myregfile $end
$var reg 32 5 \registers[20] [31:0] $end
$upscope $end
$upscope $end
$upscope $end
$scope module cpu_tb $end
$scope module mycpu $end
$scope module myregfile $end
$var reg 32 6 \registers[21] [31:0] $end
$upscope $end
$upscope $end
$upscope $end
$scope module cpu_tb $end
$scope module mycpu $end
$scope module myregfile $end
$var reg 32 7 \registers[22] [31:0] $end
$upscope $end
$upscope $end
$upscope $end
$scope module cpu_tb $end
$scope module mycpu $end
$scope module myregfile $end
$var reg 32 8 \registers[23] [31:0] $end
$upscope $end
$upscope $end
$upscope $end
$scope module cpu_tb $end
$scope module mycpu $end
$scope module myregfile $end
$var reg 32 9 \registers[24] [31:0] $end
$upscope $end
$upscope $end
$upscope $end
$scope module cpu_tb $end
$scope module mycpu $end
$scope module myregfile $end
$var reg 32 : \registers[25] [31:0] $end
$upscope $end
$upscope $end
$upscope $end
$scope module cpu_tb $end
$scope module mycpu $end
$scope module myregfile $end
$var reg 32 ; \registers[26] [31:0] $end
$upscope $end
$upscope $end
$upscope $end
$scope module cpu_tb $end
$scope module mycpu $end
$scope module myregfile $end
$var reg 32 < \registers[27] [31:0] $end
$upscope $end
$upscope $end
$upscope $end
$scope module cpu_tb $end
$scope module mycpu $end
$scope module myregfile $end
$var reg 32 = \registers[28] [31:0] $end
$upscope $end
$upscope $end
$upscope $end
$scope module cpu_tb $end
$scope module mycpu $end
$scope module myregfile $end
$var reg 32 > \registers[29] [31:0] $end
$upscope $end
$upscope $end
$upscope $end
$scope module cpu_tb $end
$scope module mycpu $end
$scope module myregfile $end
$var reg 32 ? \registers[30] [31:0] $end
$upscope $end
$upscope $end
$upscope $end
$scope module cpu_tb $end
$scope module mycpu $end
$scope module myregfile $end
$var reg 32 @ \registers[31] [31:0] $end
$upscope $end
$upscope $end
$upscope $end
$scope module cpu_tb $end
$var reg 19 A \instr_mem[0] [18:0] $end
$upscope $end
$scope module cpu_tb $end
$var reg 19 B \instr_mem[1] [18:0] $end
$upscope $end
$scope module cpu_tb $end
$var reg 19 C \instr_mem[2] [18:0] $end
$upscope $end
$scope module cpu_tb $end
$var reg 19 D \instr_mem[3] [18:0] $end
$upscope $end
$scope module cpu_tb $end
$var reg 19 E \instr_mem[4] [18:0] $end
$upscope $end
$scope module cpu_tb $end
$var reg 19 F \instr_mem[5] [18:0] $end
$upscope $end
$scope module cpu_tb $end
$var reg 19 G \instr_mem[6] [18:0] $end
$upscope $end
$scope module cpu_tb $end
$var reg 19 H \instr_mem[7] [18:0] $end
$upscope $end
$scope module cpu_tb $end
$var reg 19 I \instr_mem[8] [18:0] $end
$upscope $end
$scope module cpu_tb $end
$var reg 19 J \instr_mem[9] [18:0] $end
$upscope $end
$scope module cpu_tb $end
$var reg 19 K \instr_mem[10] [18:0] $end
$upscope $end
$scope module cpu_tb $end
$var reg 19 L \instr_mem[11] [18:0] $end
$upscope $end
$scope module cpu_tb $end
$var reg 19 M \instr_mem[12] [18:0] $end
$upscope $end
$scope module cpu_tb $end
$var reg 19 N \instr_mem[13] [18:0] $end
$upscope $end
$scope module cpu_tb $end
$var reg 19 O \instr_mem[14] [18:0] $end
$upscope $end
$scope module cpu_tb $end
$var reg 19 P \instr_mem[15] [18:0] $end
$upscope $end
$scope module cpu_tb $end
$var reg 19 Q \instr_mem[16] [18:0] $end
$upscope $end
$scope module cpu_tb $end
$var reg 19 R \instr_mem[17] [18:0] $end
$upscope $end
$scope module cpu_tb $end
$var reg 19 S \instr_mem[18] [18:0] $end
$upscope $end
$scope module cpu_tb $end
$var reg 19 T \instr_mem[19] [18:0] $end
$upscope $end
$scope module cpu_tb $end
$var wire 32 U PC [31:0] $end
$var wire 19 V INSTRUCTION [18:0] $end
$var reg 1 W CLK $end
$var reg 1 X RESET $end
$var integer 32 Y i [31:0] $end
$scope module mycpu $end
$var wire 1 W CLK $end
$var wire 19 Z INSTRUCTION [18:0] $end
$var wire 1 [ OR_OUT $end
$var wire 1 X RESET $end
$var wire 1 \ ZERO $end
$var wire 1 ] WRITE_ENABLE $end
$var wire 32 ^ SIGN_EXTENDED_IMM [31:0] $end
$var wire 32 _ OUT2 [31:0] $end
$var wire 32 ` OUT1 [31:0] $end
$var wire 32 a NEXTPC2 [31:0] $end
$var wire 32 b NEXTPC [31:0] $end
$var wire 1 c IMM_SELECT $end
$var wire 32 d IMM_RESULT [31:0] $end
$var wire 1 e BRAZ $end
$var wire 1 f BRAUNCOND $end
$var wire 1 g BRANZ $end
$var wire 1 h AND_OUT2 $end
$var wire 1 i AND_OUT $end
$var wire 32 j ALU_OUT [31:0] $end
$var wire 3 k ALUOP [2:0] $end
$var reg 32 l PC [31:0] $end
$scope module a1 $end
$var wire 1 i OUTPUT $end
$var wire 1 \ INPUT2 $end
$var wire 1 e INPUT1 $end
$upscope $end
$scope module a2 $end
$var wire 1 m INPUT2 $end
$var wire 1 h OUTPUT $end
$var wire 1 g INPUT1 $end
$upscope $end
$scope module adr $end
$var wire 32 n ONE [31:0] $end
$var wire 32 o PC [31:0] $end
$var wire 32 p NEXTPC [31:0] $end
$upscope $end
$scope module alu $end
$var wire 1 \ ZERO $end
$var wire 32 q SUB_OUT [31:0] $end
$var wire 3 r SELECT [2:0] $end
$var wire 32 s OR_OUT [31:0] $end
$var wire 32 t FORWARD_OUT [31:0] $end
$var wire 32 u DATA2 [31:0] $end
$var wire 32 v DATA1 [31:0] $end
$var wire 32 w AND_OUT [31:0] $end
$var wire 32 x ADD_OUT [31:0] $end
$var reg 32 y RESULT [31:0] $end
$scope module add1 $end
$var wire 32 z DATA2 [31:0] $end
$var wire 32 { DATA1 [31:0] $end
$var wire 32 | ADD_OUT [31:0] $end
$upscope $end
$scope module and1 $end
$var wire 32 } AND_OUT [31:0] $end
$var wire 32 ~ DATA2 [31:0] $end
$var wire 32 !" DATA1 [31:0] $end
$upscope $end
$scope module fwd1 $end
$var wire 32 "" FORWARD_OUT [31:0] $end
$var wire 32 #" DATA2 [31:0] $end
$upscope $end
$scope module or1 $end
$var wire 32 $" OR_OUT [31:0] $end
$var wire 32 %" DATA2 [31:0] $end
$var wire 32 &" DATA1 [31:0] $end
$upscope $end
$scope module sub1 $end
$var wire 32 '" DATA2 [31:0] $end
$var wire 32 (" DATA1 [31:0] $end
$var wire 32 )" ADD_OUT [31:0] $end
$upscope $end
$upscope $end
$scope module immediate_or_reg $end
$var wire 1 c SELECT $end
$var wire 32 *" INPUT2 [31:0] $end
$var wire 32 +" INPUT1 [31:0] $end
$var reg 32 ," OUTPUT [31:0] $end
$upscope $end
$scope module jump_mux $end
$var wire 32 -" INPUT1 [31:0] $end
$var wire 1 [ SELECT $end
$var wire 32 ." INPUT2 [31:0] $end
$var reg 32 /" OUTPUT [31:0] $end
$upscope $end
$scope module mucu $end
$var wire 4 0" OPCODE [3:0] $end
$var reg 3 1" ALUOP [2:0] $end
$var reg 1 g BRANZ $end
$var reg 1 f BRAUNCOND $end
$var reg 1 e BRAZ $end
$var reg 1 c MUXIMM $end
$var reg 1 ] WRITEENABLE $end
$upscope $end
$scope module myregfile $end
$var wire 1 W CLK $end
$var wire 32 2" IN [31:0] $end
$var wire 5 3" INADDRESS [4:0] $end
$var wire 32 4" OUT1 [31:0] $end
$var wire 5 5" OUT1ADDRESS [4:0] $end
$var wire 32 6" OUT2 [31:0] $end
$var wire 5 7" OUT2ADDRESS [4:0] $end
$var wire 1 X RESET $end
$var wire 1 ] WRITE $end
$var integer 32 8" i [31:0] $end
$var integer 32 9" regNum [31:0] $end
$upscope $end
$scope module signex $end
$var wire 5 :" CURRENT_VAL [4:0] $end
$var wire 32 ;" NEW_VAL [31:0] $end
$upscope $end
$upscope $end
$upscope $end
$enddefinitions $end
#0
$dumpvars
b0xxxxx ;"
bx :"
bx 9"
b100000 8"
bx 7"
bx 6"
bx 5"
bx 4"
bx 3"
bx 2"
bx 1"
bx 0"
bx /"
b0xxxxx ."
bx -"
bx ,"
bx +"
b0xxxxx *"
bx )"
bx ("
bx '"
bx &"
bx %"
bx $"
bx #"
bx ""
bx !"
bx ~
bx }
bx |
bx {
bx z
bx y
bx x
bx w
bx v
bx u
bx t
bx s
bx r
bx q
bx p
bx o
b1 n
xm
bx l
bx k
bx j
xi
xh
xg
xf
xe
bx d
xc
bx b
bx a
bx `
bx _
b0xxxxx ^
x]
x\
x[
bx Z
b10100 Y
1X
0W
bx V
bx U
b1011011010001011011 T
b10010010000010010 S
b1101101100001101101 R
b110110110000110110 Q
b1001001000001001001 P
b1110000001110 O
b1110000001110000 N
b1110000001110000001 M
b100100100100100100 L
b1011011011011011011 K
b10010010010010010 J
b1101101101101101101 I
b110110110110110110 H
b1001001001001001001 G
b1110001110001110 F
b1110001110001110001 E
b100000011xxxxx00010 D
b1000000100001000010 C
b1000000010001000001 B
b1000000010001000001 A
bx @
bx ?
bx >
bx =
bx <
bx ;
bx :
bx 9
bx 8
bx 7
bx 6
bx 5
bx 4
bx 3
bx 2
bx 1
bx 0
bx /
bx .
bx -
bx ,
bx +
bx *
bx )
bx (
bx '
bx &
bx %
bx $
bx #
bx "
bx !
$end
#4
b0 U
b0 l
b0 o
1W
#5
b0 @
b0 ?
b0 >
b0 =
b0 <
b0 ;
b0 :
b0 9
b0 8
b0 7
b0 6
b0 5
b0 4
b0 3
b0 2
b0 1
b0 0
b0 /
b0 .
b0 -
b0 ,
b0 +
b0 *
b0 )
b0 (
b0 '
b0 &
b0 %
b0 $
b0 #
b0 "
b0 !
b100000 9"
b1 b
b1 p
b1 -"
#6
b1000 0"
b1 3"
b10 5"
b1 7"
b1 ^
b1 *"
b1 ."
b1 ;"
b1 :"
b1000000010001000001 V
b1000000010001000001 Z
0X
#7
b1 a
b1 /"
0[
0h
0i
b1 d
b1 u
b1 z
b1 ~
b1 #"
b1 %"
b1 '"
b1 ,"
0f
0g
0e
1]
b100 k
b100 r
b100 1"
1c
#8
1m
0\
b1 j
b1 y
b1 2"
bx1 s
bx1 $"
b0x w
b0x }
b1 t
b1 ""
b0 `
b0 v
b0 {
b0 !"
b0 &"
b0 ("
b0 4"
b0 _
b0 +"
b0 6"
0W
#9
b1 s
b1 $"
b0 w
b0 }
#10
b1 q
b1 )"
b11111111111111111111111111111111 x
b11111111111111111111111111111111 |
#12
1W
#13
b1 "
b1 U
b1 l
b1 o
#14
b10 a
b10 /"
b10 b
b10 p
b10 -"
#15
b1 _
b1 +"
b1 6"
#16
0W
#20
1W
#21
b1 "
b10 U
b10 l
b10 o
#22
b11 a
b11 /"
b11 b
b11 p
b11 -"
#23
b10 d
b10 u
b10 z
b10 ~
b10 #"
b10 %"
b10 '"
b10 ,"
b10 3"
b10 7"
b10 ^
b10 *"
b10 ."
b10 ;"
b10 :"
b1000000100001000010 V
b1000000100001000010 Z
#24
b10 j
b10 y
b10 2"
b10 s
b10 $"
b10 t
b10 ""
0W
#25
b10 q
b10 )"
b11111111111111111111111111111110 x
b11111111111111111111111111111110 |
b0 _
b0 +"
b0 6"
#28
1W
#29
b10 #
b11 U
b11 l
b11 o
#30
b100 a
b100 /"
b100 b
b100 p
b100 -"
#31
b11 3"
bx 5"
b10 `
b10 v
b10 {
b10 !"
b10 &"
b10 ("
b10 4"
b10 _
b10 +"
b10 6"
b100000011xxxxx00010 V
b100000011xxxxx00010 Z
#32
b10 w
b10 }
0W
#33
bx `
bx v
bx {
bx !"
bx &"
bx ("
bx 4"
b100 q
b100 )"
b0 x
b0 |
#34
bx1x s
bx1x $"
b0x0 w
b0x0 }
#35
bx q
bx )"
bx x
bx |
#36
1W
#37
b10 $
b100 U
b100 l
b100 o
#38
b101 a
b101 /"
b101 b
b101 p
b101 -"
#39
b10001 d
b10001 u
b10001 z
b10001 ~
b10001 #"
b10001 %"
b10001 '"
b10001 ,"
b1110 0"
b111 3"
b11 5"
b10001 7"
b10001 ^
b10001 *"
b10001 ."
b10001 ;"
b10001 :"
b1110001110001110001 V
b1110001110001110001 Z
#40
xi
0m
1\
x[
0h
b0 j
b0 y
b0 2"
bx1xxx1 s
bx1xxx1 $"
b0x000x w
b0x000x }
xf
xg
xe
x]
bx k
bx r
bx 1"
xc
b10001 t
b10001 ""
0W
#41
b10 `
b10 v
b10 {
b10 !"
b10 &"
b10 ("
b10 4"
b0 _
b0 +"
b0 6"
#42
b10011 s
b10011 $"
b0 w
b0 }
#43
b10011 q
b10011 )"
b11111111111111111111111111110001 x
b11111111111111111111111111110001 |
#44
1W
#45
b101 U
b101 l
b101 o
#46
b110 b
b110 p
b110 -"
#47
b1 0"
b11000 3"
b11100 5"
b1110 7"
b1110 ^
b1110 *"
b1110 ."
b1110 ;"
b1110 :"
b1110001110001110 V
b1110001110001110 Z
#48
1m
b110 a
b110 /"
0\
0[
0i
b11111111111111111111111111110001 j
b11111111111111111111111111110001 y
b11111111111111111111111111110001 2"
b1110 d
b1110 u
b1110 z
b1110 ~
b1110 #"
b1110 %"
b1110 '"
b1110 ,"
0f
0g
0e
1]
b0 k
b0 r
b0 1"
1c
0W
#49
b1110 s
b1110 $"
b10 w
b10 }
b1110 t
b1110 ""
b0 `
b0 v
b0 {
b0 !"
b0 &"
b0 ("
b0 4"
#50
b0 w
b0 }
#51
b11111111111111111111111111110010 j
b11111111111111111111111111110010 y
b11111111111111111111111111110010 2"
b1110 q
b1110 )"
b11111111111111111111111111110010 x
b11111111111111111111111111110010 |
#52
1W
#53
b11111111111111111111111111110010 9
b110 U
b110 l
b110 o
#54
b111 a
b111 /"
b111 b
b111 p
b111 -"
#55
b1001 d
b1001 u
b1001 z
b1001 ~
b1001 #"
b1001 %"
b1001 '"
b1001 ,"
b1001 0"
b100 3"
b10010 5"
b1001 7"
b1001 ^
b1001 *"
b1001 ."
b1001 ;"
b1001 :"
b1001001001001001001 V
b1001001001001001001 Z
#56
b111 a
b111 /"
0m
0[
1\
0h
b0 j
b0 y
b0 2"
b1001 s
b1001 $"
1g
x]
bx k
bx r
bx 1"
xc
b1001 t
b1001 ""
0W
#57
b1001 q
b1001 )"
b11111111111111111111111111110111 x
b11111111111111111111111111110111 |
#60
1W
#61
b111 U
b111 l
b111 o
#62
b1000 a
b1000 /"
b1000 b
b1000 p
b1000 -"
#63
b110 0"
b11011 3"
b1101 5"
b10110 7"
b10110 ^
b10110 *"
b10110 ."
b10110 ;"
b10110 :"
b110110110110110110 V
b110110110110110110 Z
#64
1m
0\
b1001 j
b1001 y
b1001 2"
b0 d
b0 u
b0 z
b0 ~
b0 #"
b0 %"
b0 '"
b0 ,"
0g
1]
b11 k
b11 r
b11 1"
0c
0W
#65
0m
1\
b0 j
b0 y
b0 2"
b0 s
b0 $"
b0 t
b0 ""
#66
b0 q
b0 )"
b0 x
b0 |
#68
1W
#69
b0 <
b1000 U
b1000 l
b1000 o
#70
b1001 a
b1001 /"
b1001 b
b1001 p
b1001 -"
#71
b1101 0"
b10110 3"
b11011 5"
b1101 7"
b1101 ^
b1101 *"
b1101 ."
b1101 ;"
b1101 :"
b1101101101101101101 V
b1101101101101101101 Z
#72
x[
xi
xf
xg
xe
x]
bx k
bx r
bx 1"
xc
0W
#73
1X
#75
0X
#76
1W
#77
b1001 U
b1001 l
b1001 o
#78
b1010 b
b1010 p
b1010 -"
